setup.py
smpplib2/__init__.py
smpplib2/client.py
smpplib2/command.py
smpplib2/command_codes.py
smpplib2/consts.py
smpplib2/exceptions.py
smpplib2/gsm.py
smpplib2/pdu.py
smpplib2/ptypes.py
smpplib2/smpp.py
smpplib2.egg-info/PKG-INFO
smpplib2.egg-info/SOURCES.txt
smpplib2.egg-info/dependency_links.txt
smpplib2.egg-info/pbr.json
smpplib2.egg-info/top_level.txt
smpplib2.egg-info/zip-safe