Metadata-Version: 1.1
Name: smpplib2
Version: 0.1.1
Summary: SMPP library for python
Home-page: https://github.com/komuW/smpplib2
Author: komuW
Author-email: komuw05@gmail.com
License: UNKNOWN
Keywords: smpplib smpplib2 python-smpplib ESME SMC PDU
Platform: UNKNOWN
Classifier: Operating System :: OS Independent
Classifier: Programming Language :: Python
Classifier: Programming Language :: Python :: 2.7
Classifier: License :: OSI Approved :: MIT License
